crytic_compile/__init__.py
crytic_compile/__main__.py
crytic_compile/compilation_unit.py
crytic_compile/crytic_compile.py
crytic_compile/py.typed
crytic_compile/source_unit.py
crytic_compile/compiler/__init__.py
crytic_compile/compiler/compiler.py
crytic_compile/cryticparser/__init__.py
crytic_compile/cryticparser/cryticparser.py
crytic_compile/cryticparser/defaults.py
crytic_compile/platform/__init__.py
crytic_compile/platform/abstract_platform.py
crytic_compile/platform/all_export.py
crytic_compile/platform/all_platforms.py
crytic_compile/platform/archive.py
crytic_compile/platform/brownie.py
crytic_compile/platform/buidler.py
crytic_compile/platform/dapp.py
crytic_compile/platform/embark.py
crytic_compile/platform/etherlime.py
crytic_compile/platform/etherscan.py
crytic_compile/platform/exceptions.py
crytic_compile/platform/foundry.py
crytic_compile/platform/hardhat.py
crytic_compile/platform/solc.py
crytic_compile/platform/solc_standard_json.py
crytic_compile/platform/standard.py
crytic_compile/platform/truffle.py
crytic_compile/platform/types.py
crytic_compile/platform/vyper.py
crytic_compile/platform/waffle.py
crytic_compile/utils/__init__.py
crytic_compile/utils/name_collision.py
crytic_compile/utils/naming.py
crytic_compile/utils/natspec.py
crytic_compile/utils/npm.py
crytic_compile/utils/subprocess.py
crytic_compile/utils/unit_tests.py
crytic_compile/utils/zip.py
crytic_compile-0.3.9.dist-info/licenses/LICENSE
crytic_compile-0.3.9.dist-info/METADATA
crytic_compile-0.3.9.dist-info/WHEEL
crytic_compile-0.3.9.dist-info/entry_points.txt
crytic_compile-0.3.9.dist-info/top_level.txt
crytic_compile-0.3.9.dist-info/RECORD
