Metadata-Version: 2.4
Name: crytic-compile
Version: 0.3.9
Summary: Util to facilitate smart contracts compilation.
Home-page: https://github.com/crytic/crytic-compile
Author: Trail of Bits
License: AGPL-3.0
Requires-Python: >=3.8,!=3.12.0
License-File: LICENSE
Requires-Dist: pycryptodome>=3.4.6
Requires-Dist: cbor2
Requires-Dist: solc-select>=v1.0.4
Provides-Extra: test
Requires-Dist: pytest; extra == "test"
Requires-Dist: pytest-cov; extra == "test"
Provides-Extra: lint
Requires-Dist: black==22.3.0; extra == "lint"
Requires-Dist: pylint==2.13.4; extra == "lint"
Requires-Dist: mypy==0.942; extra == "lint"
Requires-Dist: darglint==1.8.0; extra == "lint"
Provides-Extra: doc
Requires-Dist: pdoc; extra == "doc"
Provides-Extra: dev
Requires-Dist: crytic-compile[doc,lint,test]; extra == "dev"
Dynamic: author
Dynamic: description
Dynamic: description-content-type
Dynamic: home-page
Dynamic: license
Dynamic: license-file
Dynamic: provides-extra
Dynamic: requires-dist
Dynamic: requires-python
Dynamic: summary
